update_checker.py
update_checker_test.py
update_checker_rg-0.20.0.dist-info/LICENSE.md
update_checker_rg-0.20.0.dist-info/METADATA
update_checker_rg-0.20.0.dist-info/WHEEL
update_checker_rg-0.20.0.dist-info/top_level.txt
update_checker_rg-0.20.0.dist-info/RECORD
