Metadata-Version: 2.1
Name: update_checker_rg
Version: 0.20.0
Summary: A python module that will check for package updates.
Home-page: https://github.com/rgathub/update_checker
Author: Rahul Gupta
License: Copyright (c) 2012, Bryce Boe
Project-URL: Homepage, https://github.com/rgathub/update_checker
Project-URL: Issues, https://github.com/rgathub/update_checker/issues
Classifier: Programming Language :: Python :: 3
Classifier: License :: OSI Approved :: BSD License
Classifier: Operating System :: OS Independent
Classifier: Intended Audience :: Developers
Classifier: Topic :: Software Development :: Libraries :: Python Modules
Requires-Python: >=3.8
License-File: LICENSE.md
Requires-Dist: requests>=2.3.0
Provides-Extra: dev
Requires-Dist: black>=22.12.0; extra == "dev"
Requires-Dist: Flake8-pyproject>=1.2.2; extra == "dev"
Requires-Dist: pytest>=7.1.0; extra == "dev"
